<?xml version="1.0" encoding="UTF-8"?>
<ref id="pcbi.1006471.ref041" class="ref">
 <span class="label" xmlns="http://www.w3.org/1999/xhtml">41</span>
 <div publication-type="journal" class="mixed-citation" xmlns="http://www.w3.org/1999/xhtml">
  <name class="name" xmlns="">
   <span class="surname" xmlns="http://www.w3.org/1999/xhtml">Trinchant</span>
   <span class="given-names" xmlns="http://www.w3.org/1999/xhtml">J-C</span>
  </name>, 
  <name class="name" xmlns="">
   <span class="surname" xmlns="http://www.w3.org/1999/xhtml">Rigaud</span>
   <span class="given-names" xmlns="http://www.w3.org/1999/xhtml">J</span>
  </name>. 
  <div class="article-title">Lactate Dehydrogenase from Rhizobium. Purification and Role in Indole Metabolism</div>. 
  <div class="source">Physiol Plant</div>. Blackwell Publishing Ltd; 
  <span class="year">1974</span>;
  <span class="volume">32</span>: 
  <span class="fpage">394</span>–
  <span class="lpage">399</span>.
 </div>
</ref>
