<?xml version="1.0" encoding="UTF-8"?>
<ref id="B24-ijerph-16-02518" class="ref">
 <span class="label" xmlns="http://www.w3.org/1999/xhtml">24.</span>
 <element-citation publication-type="journal" class="element-citation">
  <person-group person-group-type="author" class="person-group">
   <name class="name">
    <span class="surname" xmlns="http://www.w3.org/1999/xhtml">Ghaedi</span>
    <span class="given-names" xmlns="http://www.w3.org/1999/xhtml">M.</span>
   </name>
   <name class="name">
    <span class="surname" xmlns="http://www.w3.org/1999/xhtml">Shokrollahi</span>
    <span class="given-names" xmlns="http://www.w3.org/1999/xhtml">A.</span>
   </name>
   <name class="name">
    <span class="surname" xmlns="http://www.w3.org/1999/xhtml">Niknam</span>
    <span class="given-names" xmlns="http://www.w3.org/1999/xhtml">K.</span>
   </name>
   <name class="name">
    <span class="surname" xmlns="http://www.w3.org/1999/xhtml">Niknam</span>
    <span class="given-names" xmlns="http://www.w3.org/1999/xhtml">E.</span>
   </name>
   <name class="name">
    <span class="surname" xmlns="http://www.w3.org/1999/xhtml">Najibi</span>
    <span class="given-names" xmlns="http://www.w3.org/1999/xhtml">A.</span>
   </name>
   <name class="name">
    <span class="surname" xmlns="http://www.w3.org/1999/xhtml">Soylak</span>
    <span class="given-names" xmlns="http://www.w3.org/1999/xhtml">M.</span>
   </name>
  </person-group>
  <div class="article-title" xmlns="http://www.w3.org/1999/xhtml">Cloud point extraction and flame atomic absorption spectrometric determination of cadmium(II), lead(II), palladium(II) and silver(I) in environmental samples</div>
  <div class="source" xmlns="http://www.w3.org/1999/xhtml">J. Hazard. Mater.</div>
  <span class="year" xmlns="http://www.w3.org/1999/xhtml">2009</span>
  <span class="volume" xmlns="http://www.w3.org/1999/xhtml">168</span>
  <span class="fpage" xmlns="http://www.w3.org/1999/xhtml">1022</span>
  <span class="lpage" xmlns="http://www.w3.org/1999/xhtml">1027</span>
  <span pub-id-type="doi" class="pub-id" xmlns="http://www.w3.org/1999/xhtml">10.1016/j.jhazmat.2009.02.130</span>
  <?supplied-pmid 19380196?>
  <span pub-id-type="pmid" class="pub-id" xmlns="http://www.w3.org/1999/xhtml">19380196</span>
 </element-citation>
</ref>
