<?xml version="1.0" encoding="UTF-8"?>
<ref id="B11-micromachines-10-00439" class="ref">
 <span class="label" xmlns="http://www.w3.org/1999/xhtml">11.</span>
 <element-citation publication-type="journal" class="element-citation">
  <person-group person-group-type="author" class="person-group">
   <name class="name">
    <span class="surname" xmlns="http://www.w3.org/1999/xhtml">Sun</span>
    <span class="given-names" xmlns="http://www.w3.org/1999/xhtml">C.</span>
   </name>
   <name class="name">
    <span class="surname" xmlns="http://www.w3.org/1999/xhtml">Gardner</span>
    <span class="given-names" xmlns="http://www.w3.org/1999/xhtml">J.S.</span>
   </name>
   <name class="name">
    <span class="surname" xmlns="http://www.w3.org/1999/xhtml">Long</span>
    <span class="given-names" xmlns="http://www.w3.org/1999/xhtml">G.</span>
   </name>
   <name class="name">
    <span class="surname" xmlns="http://www.w3.org/1999/xhtml">Bajracharya</span>
    <span class="given-names" xmlns="http://www.w3.org/1999/xhtml">C.</span>
   </name>
   <name class="name">
    <span class="surname" xmlns="http://www.w3.org/1999/xhtml">Thurber</span>
    <span class="given-names" xmlns="http://www.w3.org/1999/xhtml">A.</span>
   </name>
   <name class="name">
    <span class="surname" xmlns="http://www.w3.org/1999/xhtml">Punnoose</span>
    <span class="given-names" xmlns="http://www.w3.org/1999/xhtml">A.</span>
   </name>
   <name class="name">
    <span class="surname" xmlns="http://www.w3.org/1999/xhtml">Rodriguez</span>
    <span class="given-names" xmlns="http://www.w3.org/1999/xhtml">R.G.</span>
   </name>
   <name class="name">
    <span class="surname" xmlns="http://www.w3.org/1999/xhtml">Pak</span>
    <span class="given-names" xmlns="http://www.w3.org/1999/xhtml">J.J.</span>
   </name>
  </person-group>
  <div class="article-title" xmlns="http://www.w3.org/1999/xhtml">Controlled stoichiometry for quaternary CuIn
   <sub>x</sub>Ga
   <sub>1−x</sub>S
   <sub>2</sub> chalcopyrite nanoparticles from single-source precursors via microwave irradiation
  </div>
  <div class="source" xmlns="http://www.w3.org/1999/xhtml">Chem. Mater.</div>
  <span class="year" xmlns="http://www.w3.org/1999/xhtml">2010</span>
  <span class="volume" xmlns="http://www.w3.org/1999/xhtml">22</span>
  <span class="fpage" xmlns="http://www.w3.org/1999/xhtml">2699</span>
  <span class="lpage" xmlns="http://www.w3.org/1999/xhtml">2701</span>
  <span pub-id-type="doi" class="pub-id" xmlns="http://www.w3.org/1999/xhtml">10.1021/cm100456t</span>
 </element-citation>
</ref>
