<?xml version="1.0" encoding="UTF-8"?>
<ref id="B6" class="ref">
 <div publication-type="journal" class="mixed-citation" xmlns="http://www.w3.org/1999/xhtml">
  <person-group person-group-type="author" class="person-group" xmlns="">
   <name class="name">
    <span class="surname" xmlns="http://www.w3.org/1999/xhtml">Aquilanti</span>
    <span class="given-names" xmlns="http://www.w3.org/1999/xhtml">V.</span>
   </name>
   <name class="name">
    <span class="surname" xmlns="http://www.w3.org/1999/xhtml">Cavalli</span>
    <span class="given-names" xmlns="http://www.w3.org/1999/xhtml">S.</span>
   </name>
   <name class="name">
    <span class="surname" xmlns="http://www.w3.org/1999/xhtml">Pirani</span>
    <span class="given-names" xmlns="http://www.w3.org/1999/xhtml">F.</span>
   </name>
   <name class="name">
    <span class="surname" xmlns="http://www.w3.org/1999/xhtml">Volpi</span>
    <span class="given-names" xmlns="http://www.w3.org/1999/xhtml">A.</span>
   </name>
   <name class="name">
    <span class="surname" xmlns="http://www.w3.org/1999/xhtml">Cappelletti</span>
    <span class="given-names" xmlns="http://www.w3.org/1999/xhtml">D.</span>
   </name>
  </person-group> (
  <span class="year">2001</span>). 
  <div class="article-title">Potential energy surfaces for F-H
   <sub>2</sub> and Cl-H
   <sub>2</sub>: long-range interactions and nonadiabatic couplings
  </div>. 
  <div class="source">J. Phys. Chem. A</div>
  <span class="volume">105</span>, 
  <span class="fpage">2401</span>–
  <span class="lpage">2409</span>. 
  <span pub-id-type="doi" class="pub-id">10.1021/jp003782r</span>
 </div>
</ref>
