<?xml version="1.0" encoding="UTF-8"?>
<ref id="B43" class="ref">
 <div publication-type="journal" class="mixed-citation" xmlns="http://www.w3.org/1999/xhtml">
  <person-group person-group-type="author" class="person-group" xmlns="">
   <name class="name">
    <span class="surname" xmlns="http://www.w3.org/1999/xhtml">Pack</span>
    <span class="given-names" xmlns="http://www.w3.org/1999/xhtml">R. T.</span>
   </name>
   <name class="name">
    <span class="surname" xmlns="http://www.w3.org/1999/xhtml">Parker</span>
    <span class="given-names" xmlns="http://www.w3.org/1999/xhtml">G. A.</span>
   </name>
  </person-group> (
  <span class="year">1987</span>). 
  <div class="article-title">Quantum reactive scattering in three dimensions using hyperspherical (aph) coordinates. theory</div>. 
  <div class="source">J. Chem. Phys.</div>
  <span class="volume">87</span>, 
  <span class="fpage">3888</span>–
  <span class="lpage">3921</span>.
 </div>
</ref>
