<?xml version="1.0" encoding="UTF-8"?>
<ref id="ref12" class="ref">
 <div publication-type="journal" id="cit12" class="mixed-citation" xmlns="http://www.w3.org/1999/xhtml">
  <name class="name" xmlns="">
   <span class="surname" xmlns="http://www.w3.org/1999/xhtml">Pizzi</span>
   <span class="given-names" xmlns="http://www.w3.org/1999/xhtml">G.</span>
  </name>; 
  <name class="name" xmlns="">
   <span class="surname" xmlns="http://www.w3.org/1999/xhtml">Cepellotti</span>
   <span class="given-names" xmlns="http://www.w3.org/1999/xhtml">A.</span>
  </name>; 
  <name class="name" xmlns="">
   <span class="surname" xmlns="http://www.w3.org/1999/xhtml">Sabatini</span>
   <span class="given-names" xmlns="http://www.w3.org/1999/xhtml">R.</span>
  </name>; 
  <name class="name" xmlns="">
   <span class="surname" xmlns="http://www.w3.org/1999/xhtml">Marzari</span>
   <span class="given-names" xmlns="http://www.w3.org/1999/xhtml">N.</span>
  </name>; 
  <name class="name" xmlns="">
   <span class="surname" xmlns="http://www.w3.org/1999/xhtml">Kozinsky</span>
   <span class="given-names" xmlns="http://www.w3.org/1999/xhtml">B.</span>
  </name>
  <div class="article-title">AiiDA: automated interactive infrastructure and database for computational science</div>. 
  <div class="source">Comput. Mater. Sci.</div>
  <span class="year">2016</span>, 
  <span class="volume">111</span>, 
  <span class="fpage">218</span>–
  <span class="lpage">230</span>
  <span pub-id-type="doi" class="pub-id">10.1016/j.commatsci.2015.09.013</span>.
 </div>
</ref>
