<?xml version="1.0" encoding="UTF-8"?>
<ref id="B18-ijms-20-03227" class="ref">
 <span class="label" xmlns="http://www.w3.org/1999/xhtml">18.</span>
 <element-citation publication-type="journal" class="element-citation">
  <person-group person-group-type="author" class="person-group">
   <name class="name">
    <span class="surname" xmlns="http://www.w3.org/1999/xhtml">Goldsmith</span>
    <span class="given-names" xmlns="http://www.w3.org/1999/xhtml">C.F.</span>
   </name>
   <name class="name">
    <span class="surname" xmlns="http://www.w3.org/1999/xhtml">Green</span>
    <span class="given-names" xmlns="http://www.w3.org/1999/xhtml">W.H.</span>
   </name>
   <name class="name">
    <span class="surname" xmlns="http://www.w3.org/1999/xhtml">Klippenstein</span>
    <span class="given-names" xmlns="http://www.w3.org/1999/xhtml">S.J.</span>
   </name>
  </person-group>
  <div class="article-title" xmlns="http://www.w3.org/1999/xhtml">Role of O-2 + QOOH in Low-Temperature Ignition of Propane. 1. Temperature and Pressure Dependent Rate Coefficients</div>
  <div class="source" xmlns="http://www.w3.org/1999/xhtml">J. Phys. Chem. A</div>
  <span class="year" xmlns="http://www.w3.org/1999/xhtml">2012</span>
  <span class="volume" xmlns="http://www.w3.org/1999/xhtml">116</span>
  <span class="fpage" xmlns="http://www.w3.org/1999/xhtml">3325</span>
  <span class="lpage" xmlns="http://www.w3.org/1999/xhtml">3346</span>
  <span pub-id-type="doi" class="pub-id" xmlns="http://www.w3.org/1999/xhtml">10.1021/jp210722w</span>
  <span pub-id-type="pmid" class="pub-id" xmlns="http://www.w3.org/1999/xhtml">22250995</span>
 </element-citation>
</ref>
