<?xml version="1.0" encoding="UTF-8"?>
<ref id="B47" class="ref">
 <div publication-type="webpage" class="mixed-citation" xmlns="http://www.w3.org/1999/xhtml">
  <person-group person-group-type="author" class="person-group" xmlns="">
   <name class="name">
    <span class="surname" xmlns="http://www.w3.org/1999/xhtml">Junior</span>
    <span class="given-names" xmlns="http://www.w3.org/1999/xhtml">A. C. do P. R.</span>
   </name>
   <name class="name">
    <span class="surname" xmlns="http://www.w3.org/1999/xhtml">Cruz</span>
    <span class="given-names" xmlns="http://www.w3.org/1999/xhtml">C.</span>
   </name>
   <name class="name">
    <span class="surname" xmlns="http://www.w3.org/1999/xhtml">Santana</span>
    <span class="given-names" xmlns="http://www.w3.org/1999/xhtml">W. S.</span>
   </name>
   <name class="name">
    <span class="surname" xmlns="http://www.w3.org/1999/xhtml">Moret</span>
    <span class="given-names" xmlns="http://www.w3.org/1999/xhtml">M. A.</span>
   </name>
  </person-group> (
  <span class="year">2019</span>). 
  <div class="source">Characterization of the non-Arrhenius behavior of supercooled liquids by modeling non-additive stochastic systems</div>. Available online at: 
  <span ext-link-type="uri" xlink:href="http://arxiv.org/abs/1903.03156" class="ext-link" xmlns:xlink="http://www.w3.org/1999/xlink">http://arxiv.org/abs/1903.03156</span> (accessed March 24, 2019).
 </div>
</ref>
