<?xml version="1.0" encoding="UTF-8"?>
<ref id="b149" class="ref">
 <span class="label" xmlns="http://www.w3.org/1999/xhtml">149</span>
 <element-citation publication-type="journal" class="element-citation">
  <person-group person-group-type="author" class="person-group">
   <name class="name">
    <span class="surname" xmlns="http://www.w3.org/1999/xhtml">Bak</span>
    <span class="given-names" xmlns="http://www.w3.org/1999/xhtml">KL</span>
   </name>
   <name class="name">
    <span class="surname" xmlns="http://www.w3.org/1999/xhtml">Koch</span>
    <span class="given-names" xmlns="http://www.w3.org/1999/xhtml">H</span>
   </name>
   <name class="name">
    <span class="surname" xmlns="http://www.w3.org/1999/xhtml">Oddershede</span>
    <span class="given-names" xmlns="http://www.w3.org/1999/xhtml">J</span>
   </name>
   <name class="name">
    <span class="surname" xmlns="http://www.w3.org/1999/xhtml">Christiansen</span>
    <span class="given-names" xmlns="http://www.w3.org/1999/xhtml">O</span>
   </name>
   <name class="name">
    <span class="surname" xmlns="http://www.w3.org/1999/xhtml">Sauer</span>
    <span class="given-names" xmlns="http://www.w3.org/1999/xhtml">SPA</span>
   </name>
  </person-group>
  <div class="article-title" xmlns="http://www.w3.org/1999/xhtml">Atomic integral driven second order polarization propagator calculations of the excitation spectra of naphthalene and anthracene</div>
  <div class="source" xmlns="http://www.w3.org/1999/xhtml">J Chem Phys</div>
  <span class="year" xmlns="http://www.w3.org/1999/xhtml">2000</span>
  <span class="volume" xmlns="http://www.w3.org/1999/xhtml">112</span>
  <span class="fpage" xmlns="http://www.w3.org/1999/xhtml">4173</span>
  <span class="lpage" xmlns="http://www.w3.org/1999/xhtml">4185</span>
 </element-citation>
</ref>
