<?xml version="1.0" encoding="UTF-8"?>
<ref-list class="ref-list">
 <div class="title" xmlns="http://www.w3.org/1999/xhtml">References</div>
 <ref id="B1-molecules-24-02285" class="ref">
  <span class="label" xmlns="http://www.w3.org/1999/xhtml">1.</span>
  <element-citation publication-type="book" class="element-citation">
   <person-group person-group-type="author" class="person-group">
    <name class="name">
     <span class="surname" xmlns="http://www.w3.org/1999/xhtml">Xie</span>
     <span class="given-names" xmlns="http://www.w3.org/1999/xhtml">G.</span>
    </name>
   </person-group>
   <div class="source" xmlns="http://www.w3.org/1999/xhtml">Mineral Processing</div>
   <span class="edition" xmlns="http://www.w3.org/1999/xhtml">3rd ed.</span>
   <span class="publisher-name" xmlns="http://www.w3.org/1999/xhtml">China University of Mining and Technology Press</span>
   <span class="publisher-loc" xmlns="http://www.w3.org/1999/xhtml">Xuzhou, China</span>
   <span class="year" xmlns="http://www.w3.org/1999/xhtml">2012</span>
   <span class="fpage" xmlns="http://www.w3.org/1999/xhtml">413</span>
   <span class="lpage" xmlns="http://www.w3.org/1999/xhtml">414</span>
  </element-citation>
 </ref>
 <ref id="B2-molecules-24-02285" class="ref">
  <span class="label" xmlns="http://www.w3.org/1999/xhtml">2.</span>
  <element-citation publication-type="journal" class="element-citation">
   <person-group person-group-type="author" class="person-group">
    <name class="name">
     <span class="surname" xmlns="http://www.w3.org/1999/xhtml">Shao</span>
     <span class="given-names" xmlns="http://www.w3.org/1999/xhtml">X.</span>
    </name>
    <name class="name">
     <span class="surname" xmlns="http://www.w3.org/1999/xhtml">Tang</span>
     <span class="given-names" xmlns="http://www.w3.org/1999/xhtml">Y.</span>
    </name>
    <name class="name">
     <span class="surname" xmlns="http://www.w3.org/1999/xhtml">Wang</span>
     <span class="given-names" xmlns="http://www.w3.org/1999/xhtml">P.</span>
    </name>
   </person-group>
   <div class="article-title" xmlns="http://www.w3.org/1999/xhtml">The ESCA study of coal pyrite and pyrite</div>
   <div class="source" xmlns="http://www.w3.org/1999/xhtml">Anal. Util. Coal Qual.</div>
   <span class="year" xmlns="http://www.w3.org/1999/xhtml">1994</span>
   <span class="volume" xmlns="http://www.w3.org/1999/xhtml">2</span>
   <span class="fpage" xmlns="http://www.w3.org/1999/xhtml">9</span>
   <span class="lpage" xmlns="http://www.w3.org/1999/xhtml">18</span>
  </element-citation>
 </ref>
 <ref id="B3-molecules-24-02285" class="ref">
  <span class="label" xmlns="http://www.w3.org/1999/xhtml">3.</span>
  <element-citation publication-type="journal" class="element-citation">
   <person-group person-group-type="author" class="person-group">
    <name class="name">
     <span class="surname" xmlns="http://www.w3.org/1999/xhtml">Wang</span>
     <span class="given-names" xmlns="http://www.w3.org/1999/xhtml">W.</span>
    </name>
   </person-group>
   <div class="article-title" xmlns="http://www.w3.org/1999/xhtml">Physical and Chemical characteristics of fine pyrite in coal</div>
   <div class="source" xmlns="http://www.w3.org/1999/xhtml">Univ. J. Geol.</div>
   <span class="year" xmlns="http://www.w3.org/1999/xhtml">2013</span>
   <span class="volume" xmlns="http://www.w3.org/1999/xhtml">19</span>
   <span class="fpage" xmlns="http://www.w3.org/1999/xhtml">601</span>
   <span class="lpage" xmlns="http://www.w3.org/1999/xhtml">602</span>
  </element-citation>
 </ref>
 <ref id="B4-molecules-24-02285" class="ref">
  <span class="label" xmlns="http://www.w3.org/1999/xhtml">4.</span>
  <element-citation publication-type="book" class="element-citation">
   <person-group person-group-type="author" class="person-group">
    <name class="name">
     <span class="surname" xmlns="http://www.w3.org/1999/xhtml">Yu</span>
     <span class="given-names" xmlns="http://www.w3.org/1999/xhtml">J.</span>
    </name>
   </person-group>
   <div class="article-title" xmlns="http://www.w3.org/1999/xhtml">Study on the Physical and Chemical Characteristics of Coal-Pyrite and its Inhibitors</div>
   <div class="source" xmlns="http://www.w3.org/1999/xhtml">Ph.D. Thesis</div>
   <span class="publisher-name" xmlns="http://www.w3.org/1999/xhtml">China University of Mining and Technology (Beijing)</span>
   <span class="publisher-loc" xmlns="http://www.w3.org/1999/xhtml">Beijing, China</span>
   <span class="year" xmlns="http://www.w3.org/1999/xhtml">2013</span>
  </element-citation>
 </ref>
 <ref id="B5-molecules-24-02285" class="ref">
  <span class="label" xmlns="http://www.w3.org/1999/xhtml">5.</span>
  <element-citation publication-type="book" class="element-citation">
   <person-group person-group-type="author" class="person-group">
    <name class="name">
     <span class="surname" xmlns="http://www.w3.org/1999/xhtml">Xi</span>
     <span class="given-names" xmlns="http://www.w3.org/1999/xhtml">P.</span>
    </name>
   </person-group>
   <div class="article-title" xmlns="http://www.w3.org/1999/xhtml">Quantum Chemistry Investigation on the Physicochemical Property of Coal Pyrite and its Inhibitory Regularities</div>
   <div class="source" xmlns="http://www.w3.org/1999/xhtml">Ph.D. Thesis</div>
   <span class="publisher-name" xmlns="http://www.w3.org/1999/xhtml">China University of Mining and Technology (Beijing)</span>
   <span class="publisher-loc" xmlns="http://www.w3.org/1999/xhtml">Beijing, China</span>
   <span class="year" xmlns="http://www.w3.org/1999/xhtml">2017</span>
  </element-citation>
 </ref>
 <ref id="B6-molecules-24-02285" class="ref">
  <span class="label" xmlns="http://www.w3.org/1999/xhtml">6.</span>
  <element-citation publication-type="journal" class="element-citation">
   <person-group person-group-type="author" class="person-group">
    <name class="name">
     <span class="surname" xmlns="http://www.w3.org/1999/xhtml">Xi</span>
     <span class="given-names" xmlns="http://www.w3.org/1999/xhtml">P.</span>
    </name>
    <name class="name">
     <span class="surname" xmlns="http://www.w3.org/1999/xhtml">Liu</span>
     <span class="given-names" xmlns="http://www.w3.org/1999/xhtml">W.</span>
    </name>
    <name class="name">
     <span class="surname" xmlns="http://www.w3.org/1999/xhtml">Han</span>
     <span class="given-names" xmlns="http://www.w3.org/1999/xhtml">Y.</span>
    </name>
   </person-group>
   <div class="article-title" xmlns="http://www.w3.org/1999/xhtml">Study on the mechanism of coal pyrite crystal lattice defects and floatability</div>
   <div class="source" xmlns="http://www.w3.org/1999/xhtml">J. China Coal Soc.</div>
   <span class="year" xmlns="http://www.w3.org/1999/xhtml">2016</span>
   <span class="volume" xmlns="http://www.w3.org/1999/xhtml">41</span>
   <span class="fpage" xmlns="http://www.w3.org/1999/xhtml">997</span>
   <span class="lpage" xmlns="http://www.w3.org/1999/xhtml">1003</span>
  </element-citation>
 </ref>
 <ref id="B7-molecules-24-02285" class="ref">
  <span class="label" xmlns="http://www.w3.org/1999/xhtml">7.</span>
  <element-citation publication-type="journal" class="element-citation">
   <person-group person-group-type="author" class="person-group">
    <name class="name">
     <span class="surname" xmlns="http://www.w3.org/1999/xhtml">Schlegel</span>
     <span class="given-names" xmlns="http://www.w3.org/1999/xhtml">P.</span>
    </name>
    <name class="name">
     <span class="surname" xmlns="http://www.w3.org/1999/xhtml">Wachter</span>
     <span class="given-names" xmlns="http://www.w3.org/1999/xhtml">P.</span>
    </name>
   </person-group>
   <div class="article-title" xmlns="http://www.w3.org/1999/xhtml">Optical properties, phonons and electronic structure of iron pyrite (FeS
    <sub>2</sub>)
   </div>
   <div class="source" xmlns="http://www.w3.org/1999/xhtml">J. Phys. C Solid State Phys.</div>
   <span class="year" xmlns="http://www.w3.org/1999/xhtml">1976</span>
   <span class="volume" xmlns="http://www.w3.org/1999/xhtml">9</span>
   <span class="fpage" xmlns="http://www.w3.org/1999/xhtml">3363</span>
   <span class="lpage" xmlns="http://www.w3.org/1999/xhtml">3369</span>
   <span pub-id-type="doi" class="pub-id" xmlns="http://www.w3.org/1999/xhtml">10.1088/0022-3719/9/17/027</span>
  </element-citation>
 </ref>
 <ref id="B8-molecules-24-02285" class="ref">
  <span class="label" xmlns="http://www.w3.org/1999/xhtml">8.</span>
  <element-citation publication-type="journal" class="element-citation">
   <person-group person-group-type="author" class="person-group">
    <name class="name">
     <span class="surname" xmlns="http://www.w3.org/1999/xhtml">Zhang</span>
     <span class="given-names" xmlns="http://www.w3.org/1999/xhtml">Y.</span>
    </name>
    <name class="name">
     <span class="surname" xmlns="http://www.w3.org/1999/xhtml">Hu</span>
     <span class="given-names" xmlns="http://www.w3.org/1999/xhtml">J.</span>
    </name>
   </person-group>
   <div class="article-title" xmlns="http://www.w3.org/1999/xhtml">Law Effect of surface stoichiometry on the band gap of the pyrite FeS2(100) surface</div>
   <div class="source" xmlns="http://www.w3.org/1999/xhtml">M. Phys. Rev. B</div>
   <span class="year" xmlns="http://www.w3.org/1999/xhtml">2012</span>
   <span class="fpage" xmlns="http://www.w3.org/1999/xhtml">085314-1-6</span>
  </element-citation>
 </ref>
 <ref id="B9-molecules-24-02285" class="ref">
  <span class="label" xmlns="http://www.w3.org/1999/xhtml">9.</span>
  <element-citation publication-type="journal" class="element-citation">
   <person-group person-group-type="author" class="person-group">
    <name class="name">
     <span class="surname" xmlns="http://www.w3.org/1999/xhtml">Sun</span>
     <span class="given-names" xmlns="http://www.w3.org/1999/xhtml">R.</span>
    </name>
    <name class="name">
     <span class="surname" xmlns="http://www.w3.org/1999/xhtml">Chan</span>
     <span class="given-names" xmlns="http://www.w3.org/1999/xhtml">M.K.Y.</span>
    </name>
    <name class="name">
     <span class="surname" xmlns="http://www.w3.org/1999/xhtml">Ceder</span>
     <span class="given-names" xmlns="http://www.w3.org/1999/xhtml">G.</span>
    </name>
   </person-group>
   <div class="article-title" xmlns="http://www.w3.org/1999/xhtml">First-principles electronic structure and relative stability of pyrite and marcasite: Implications for photovoltaic performance</div>
   <div class="source" xmlns="http://www.w3.org/1999/xhtml">Phys. Rev. B</div>
   <span class="year" xmlns="http://www.w3.org/1999/xhtml">2011</span>
   <span class="fpage" xmlns="http://www.w3.org/1999/xhtml">235311-1-12</span>
   <span pub-id-type="doi" class="pub-id" xmlns="http://www.w3.org/1999/xhtml">10.1103/PhysRevB.83.235311</span>
  </element-citation>
 </ref>
 <ref id="B10-molecules-24-02285" class="ref">
  <span class="label" xmlns="http://www.w3.org/1999/xhtml">10.</span>
  <element-citation publication-type="journal" class="element-citation">
   <person-group person-group-type="author" class="person-group">
    <name class="name">
     <span class="surname" xmlns="http://www.w3.org/1999/xhtml">Li</span>
     <span class="given-names" xmlns="http://www.w3.org/1999/xhtml">Y.</span>
    </name>
    <name class="name">
     <span class="surname" xmlns="http://www.w3.org/1999/xhtml">Chen</span>
     <span class="given-names" xmlns="http://www.w3.org/1999/xhtml">J.H.</span>
    </name>
    <name class="name">
     <span class="surname" xmlns="http://www.w3.org/1999/xhtml">Zhao</span>
     <span class="given-names" xmlns="http://www.w3.org/1999/xhtml">C.H.</span>
    </name>
   </person-group>
   <div class="article-title" xmlns="http://www.w3.org/1999/xhtml">Influence of external electric field on the electronic structure and optical properties of pyrite</div>
   <div class="source" xmlns="http://www.w3.org/1999/xhtml">Rsc Adv.</div>
   <span class="year" xmlns="http://www.w3.org/1999/xhtml">2017</span>
   <span class="volume" xmlns="http://www.w3.org/1999/xhtml">7</span>
   <span class="fpage" xmlns="http://www.w3.org/1999/xhtml">56676</span>
   <span class="lpage" xmlns="http://www.w3.org/1999/xhtml">56681</span>
   <span pub-id-type="doi" class="pub-id" xmlns="http://www.w3.org/1999/xhtml">10.1039/C7RA10815J</span>
  </element-citation>
 </ref>
 <ref id="B11-molecules-24-02285" class="ref">
  <span class="label" xmlns="http://www.w3.org/1999/xhtml">11.</span>
  <element-citation publication-type="journal" class="element-citation">
   <person-group person-group-type="author" class="person-group">
    <name class="name">
     <span class="surname" xmlns="http://www.w3.org/1999/xhtml">Chen</span>
     <span class="given-names" xmlns="http://www.w3.org/1999/xhtml">J.</span>
    </name>
    <name class="name">
     <span class="surname" xmlns="http://www.w3.org/1999/xhtml">Long</span>
     <span class="given-names" xmlns="http://www.w3.org/1999/xhtml">X.</span>
    </name>
    <name class="name">
     <span class="surname" xmlns="http://www.w3.org/1999/xhtml">Chen</span>
     <span class="given-names" xmlns="http://www.w3.org/1999/xhtml">Y.</span>
    </name>
   </person-group>
   <div class="article-title" xmlns="http://www.w3.org/1999/xhtml">Comparison of Multilayer Water Adsorption on the Hydrophobic Galena (PbS) and Hydrophilic Pyrite (FeS
    <sub>2</sub>) Surface: A DFT Study
   </div>
   <div class="source" xmlns="http://www.w3.org/1999/xhtml">J. Phys. Chem. C</div>
   <span class="year" xmlns="http://www.w3.org/1999/xhtml">2014</span>
   <span class="volume" xmlns="http://www.w3.org/1999/xhtml">118</span>
   <span class="fpage" xmlns="http://www.w3.org/1999/xhtml">11657</span>
   <span class="lpage" xmlns="http://www.w3.org/1999/xhtml">11665</span>
   <span pub-id-type="doi" class="pub-id" xmlns="http://www.w3.org/1999/xhtml">10.1021/jp5000478</span>
  </element-citation>
 </ref>
 <ref id="B12-molecules-24-02285" class="ref">
  <span class="label" xmlns="http://www.w3.org/1999/xhtml">12.</span>
  <element-citation publication-type="journal" class="element-citation">
   <person-group person-group-type="author" class="person-group">
    <name class="name">
     <span class="surname" xmlns="http://www.w3.org/1999/xhtml">Chen</span>
     <span class="given-names" xmlns="http://www.w3.org/1999/xhtml">J.</span>
    </name>
    <name class="name">
     <span class="surname" xmlns="http://www.w3.org/1999/xhtml">Li</span>
     <span class="given-names" xmlns="http://www.w3.org/1999/xhtml">Y.</span>
    </name>
    <name class="name">
     <span class="surname" xmlns="http://www.w3.org/1999/xhtml">Zhong</span>
     <span class="given-names" xmlns="http://www.w3.org/1999/xhtml">S.</span>
    </name>
   </person-group>
   <div class="article-title" xmlns="http://www.w3.org/1999/xhtml">Quantum chemical study of adsorption of hydroxyl and hydroxyl calcium on pyrite (100) surface bearing vacancy defects</div>
   <div class="source" xmlns="http://www.w3.org/1999/xhtml">Chinese J. Nonferrous Metals.</div>
   <span class="year" xmlns="http://www.w3.org/1999/xhtml">2013</span>
   <span class="volume" xmlns="http://www.w3.org/1999/xhtml">23</span>
   <span class="fpage" xmlns="http://www.w3.org/1999/xhtml">859</span>
   <span class="lpage" xmlns="http://www.w3.org/1999/xhtml">865</span>
  </element-citation>
 </ref>
 <ref id="B13-molecules-24-02285" class="ref">
  <span class="label" xmlns="http://www.w3.org/1999/xhtml">13.</span>
  <element-citation publication-type="journal" class="element-citation">
   <person-group person-group-type="author" class="person-group">
    <name class="name">
     <span class="surname" xmlns="http://www.w3.org/1999/xhtml">Chen</span>
     <span class="given-names" xmlns="http://www.w3.org/1999/xhtml">J.</span>
    </name>
    <name class="name">
     <span class="surname" xmlns="http://www.w3.org/1999/xhtml">Lan</span>
     <span class="given-names" xmlns="http://www.w3.org/1999/xhtml">L.</span>
    </name>
    <name class="name">
     <span class="surname" xmlns="http://www.w3.org/1999/xhtml">Chen</span>
     <span class="given-names" xmlns="http://www.w3.org/1999/xhtml">Y.</span>
    </name>
   </person-group>
   <div class="article-title" xmlns="http://www.w3.org/1999/xhtml">Computational simulation of adsorption and thermodynamic study of xanthate dithiophosphate and dithiocarbamate on galena and pyrite surfaces</div>
   <div class="source" xmlns="http://www.w3.org/1999/xhtml">Min. Eng.</div>
   <span class="year" xmlns="http://www.w3.org/1999/xhtml">2013</span>
   <span class="volume" xmlns="http://www.w3.org/1999/xhtml">46–47</span>
   <span class="fpage" xmlns="http://www.w3.org/1999/xhtml">136</span>
   <span class="lpage" xmlns="http://www.w3.org/1999/xhtml">143</span>
   <span pub-id-type="doi" class="pub-id" xmlns="http://www.w3.org/1999/xhtml">10.1016/j.mineng.2013.03.015</span>
  </element-citation>
 </ref>
 <ref id="B14-molecules-24-02285" class="ref">
  <span class="label" xmlns="http://www.w3.org/1999/xhtml">14.</span>
  <element-citation publication-type="journal" class="element-citation">
   <person-group person-group-type="author" class="person-group">
    <name class="name">
     <span class="surname" xmlns="http://www.w3.org/1999/xhtml">Zhao</span>
     <span class="given-names" xmlns="http://www.w3.org/1999/xhtml">C.</span>
    </name>
    <name class="name">
     <span class="surname" xmlns="http://www.w3.org/1999/xhtml">Chen</span>
     <span class="given-names" xmlns="http://www.w3.org/1999/xhtml">J.</span>
    </name>
    <name class="name">
     <span class="surname" xmlns="http://www.w3.org/1999/xhtml">Li</span>
     <span class="given-names" xmlns="http://www.w3.org/1999/xhtml">Y.</span>
    </name>
    <name class="name">
     <span class="surname" xmlns="http://www.w3.org/1999/xhtml">Huang</span>
     <span class="given-names" xmlns="http://www.w3.org/1999/xhtml">D.W.</span>
    </name>
    <name class="name">
     <span class="surname" xmlns="http://www.w3.org/1999/xhtml">Li</span>
     <span class="given-names" xmlns="http://www.w3.org/1999/xhtml">W.</span>
    </name>
   </person-group>
   <div class="article-title" xmlns="http://www.w3.org/1999/xhtml">DFT study of interactions between calcium hydroxyl ions and pyrite, marcasite, pyrrhotite surfaces</div>
   <div class="source" xmlns="http://www.w3.org/1999/xhtml">Appl. Surf. Sci.</div>
   <span class="year" xmlns="http://www.w3.org/1999/xhtml">2015</span>
   <span class="volume" xmlns="http://www.w3.org/1999/xhtml">355</span>
   <span class="fpage" xmlns="http://www.w3.org/1999/xhtml">577</span>
   <span class="lpage" xmlns="http://www.w3.org/1999/xhtml">581</span>
   <span pub-id-type="doi" class="pub-id" xmlns="http://www.w3.org/1999/xhtml">10.1016/j.apsusc.2015.07.081</span>
  </element-citation>
 </ref>
 <ref id="B15-molecules-24-02285" class="ref">
  <span class="label" xmlns="http://www.w3.org/1999/xhtml">15.</span>
  <element-citation publication-type="journal" class="element-citation">
   <person-group person-group-type="author" class="person-group">
    <name class="name">
     <span class="surname" xmlns="http://www.w3.org/1999/xhtml">Li</span>
     <span class="given-names" xmlns="http://www.w3.org/1999/xhtml">Y.</span>
    </name>
    <name class="name">
     <span class="surname" xmlns="http://www.w3.org/1999/xhtml">Chen</span>
     <span class="given-names" xmlns="http://www.w3.org/1999/xhtml">J.</span>
    </name>
    <name class="name">
     <span class="surname" xmlns="http://www.w3.org/1999/xhtml">Lan</span>
     <span class="given-names" xmlns="http://www.w3.org/1999/xhtml">L.</span>
    </name>
   </person-group>
   <div class="article-title" xmlns="http://www.w3.org/1999/xhtml">Adsorption of O
    <sub>2</sub> on pyrite and galena surfaces
   </div>
   <div class="source" xmlns="http://www.w3.org/1999/xhtml">Chin. J. Nonferrous Met.</div>
   <span class="year" xmlns="http://www.w3.org/1999/xhtml">2012</span>
   <span class="volume" xmlns="http://www.w3.org/1999/xhtml">22</span>
   <span class="fpage" xmlns="http://www.w3.org/1999/xhtml">1184</span>
   <span class="lpage" xmlns="http://www.w3.org/1999/xhtml">1194</span>
  </element-citation>
 </ref>
 <ref id="B16-molecules-24-02285" class="ref">
  <span class="label" xmlns="http://www.w3.org/1999/xhtml">16.</span>
  <element-citation publication-type="book" class="element-citation">
   <person-group person-group-type="author" class="person-group">
    <name class="name">
     <span class="surname" xmlns="http://www.w3.org/1999/xhtml">Li</span>
     <span class="given-names" xmlns="http://www.w3.org/1999/xhtml">Y.</span>
    </name>
   </person-group>
   <div class="article-title" xmlns="http://www.w3.org/1999/xhtml">First Principle Study of the Influences of Lattice Defects on the Electronic Structures and Flotation Behaviors of Pyrite Crystal</div>
   <div class="source" xmlns="http://www.w3.org/1999/xhtml">Ph.D. Thesis</div>
   <span class="publisher-name" xmlns="http://www.w3.org/1999/xhtml">Guangxi University</span>
   <span class="publisher-loc" xmlns="http://www.w3.org/1999/xhtml">Nanning, China</span>
   <span class="year" xmlns="http://www.w3.org/1999/xhtml">2011</span>
  </element-citation>
 </ref>
 <ref id="B17-molecules-24-02285" class="ref">
  <span class="label" xmlns="http://www.w3.org/1999/xhtml">17.</span>
  <element-citation publication-type="journal" class="element-citation">
   <person-group person-group-type="author" class="person-group">
    <name class="name">
     <span class="surname" xmlns="http://www.w3.org/1999/xhtml">Segall</span>
     <span class="given-names" xmlns="http://www.w3.org/1999/xhtml">M.D.</span>
    </name>
    <name class="name">
     <span class="surname" xmlns="http://www.w3.org/1999/xhtml">Lindan</span>
     <span class="given-names" xmlns="http://www.w3.org/1999/xhtml">P.J.D.</span>
    </name>
    <name class="name">
     <span class="surname" xmlns="http://www.w3.org/1999/xhtml">Probert</span>
     <span class="given-names" xmlns="http://www.w3.org/1999/xhtml">M.J.</span>
    </name>
    <name class="name">
     <span class="surname" xmlns="http://www.w3.org/1999/xhtml">Pickard</span>
     <span class="given-names" xmlns="http://www.w3.org/1999/xhtml">C.J.</span>
    </name>
    <name class="name">
     <span class="surname" xmlns="http://www.w3.org/1999/xhtml">Hasnip</span>
     <span class="given-names" xmlns="http://www.w3.org/1999/xhtml">P.J.</span>
    </name>
    <name class="name">
     <span class="surname" xmlns="http://www.w3.org/1999/xhtml">Clark</span>
     <span class="given-names" xmlns="http://www.w3.org/1999/xhtml">S.J.</span>
    </name>
    <name class="name">
     <span class="surname" xmlns="http://www.w3.org/1999/xhtml">Payne</span>
     <span class="given-names" xmlns="http://www.w3.org/1999/xhtml">M.C.</span>
    </name>
   </person-group>
   <div class="article-title" xmlns="http://www.w3.org/1999/xhtml">First-principles simulation: ideas, illustrated and the CASTEP code</div>
   <div class="source" xmlns="http://www.w3.org/1999/xhtml">J. Phys. Condens. Matter.</div>
   <span class="year" xmlns="http://www.w3.org/1999/xhtml">2002</span>
   <span class="volume" xmlns="http://www.w3.org/1999/xhtml">14</span>
   <span class="fpage" xmlns="http://www.w3.org/1999/xhtml">2717</span>
   <span class="lpage" xmlns="http://www.w3.org/1999/xhtml">2744</span>
   <span pub-id-type="doi" class="pub-id" xmlns="http://www.w3.org/1999/xhtml">10.1088/0953-8984/14/11/301</span>
  </element-citation>
 </ref>
 <ref id="B18-molecules-24-02285" class="ref">
  <span class="label" xmlns="http://www.w3.org/1999/xhtml">18.</span>
  <element-citation publication-type="journal" class="element-citation">
   <person-group person-group-type="author" class="person-group">
    <name class="name">
     <span class="surname" xmlns="http://www.w3.org/1999/xhtml">Perdew</span>
     <span class="given-names" xmlns="http://www.w3.org/1999/xhtml">J.P.</span>
    </name>
    <name class="name">
     <span class="surname" xmlns="http://www.w3.org/1999/xhtml">Chevary</span>
     <span class="given-names" xmlns="http://www.w3.org/1999/xhtml">J.A.</span>
    </name>
    <name class="name">
     <span class="surname" xmlns="http://www.w3.org/1999/xhtml">Vosko</span>
     <span class="given-names" xmlns="http://www.w3.org/1999/xhtml">S.H.</span>
    </name>
    <name class="name">
     <span class="surname" xmlns="http://www.w3.org/1999/xhtml">Jackson</span>
     <span class="given-names" xmlns="http://www.w3.org/1999/xhtml">K.A.</span>
    </name>
    <name class="name">
     <span class="surname" xmlns="http://www.w3.org/1999/xhtml">Pederson</span>
     <span class="given-names" xmlns="http://www.w3.org/1999/xhtml">M.R.</span>
    </name>
    <name class="name">
     <span class="surname" xmlns="http://www.w3.org/1999/xhtml">Singh</span>
     <span class="given-names" xmlns="http://www.w3.org/1999/xhtml">D.J.</span>
    </name>
    <name class="name">
     <span class="surname" xmlns="http://www.w3.org/1999/xhtml">Fiolhais</span>
     <span class="given-names" xmlns="http://www.w3.org/1999/xhtml">C.</span>
    </name>
   </person-group>
   <div class="article-title" xmlns="http://www.w3.org/1999/xhtml">Atoms, molecules, solids, and surfaces: Applications of the generalized gradient approximation for exchange and correlation</div>
   <div class="source" xmlns="http://www.w3.org/1999/xhtml">Phy. Rev. B Condens. Matter Mater. Phys.</div>
   <span class="year" xmlns="http://www.w3.org/1999/xhtml">1992</span>
   <span class="volume" xmlns="http://www.w3.org/1999/xhtml">46</span>
   <span class="fpage" xmlns="http://www.w3.org/1999/xhtml">6671</span>
   <span class="lpage" xmlns="http://www.w3.org/1999/xhtml">6687</span>
   <span pub-id-type="doi" class="pub-id" xmlns="http://www.w3.org/1999/xhtml">10.1103/PhysRevB.46.6671</span>
   <?supplied-pmid 10002368?>
   <span pub-id-type="pmid" class="pub-id" xmlns="http://www.w3.org/1999/xhtml">10002368</span>
  </element-citation>
 </ref>
 <ref id="B19-molecules-24-02285" class="ref">
  <span class="label" xmlns="http://www.w3.org/1999/xhtml">19.</span>
  <element-citation publication-type="journal" class="element-citation">
   <person-group person-group-type="author" class="person-group">
    <name class="name">
     <span class="surname" xmlns="http://www.w3.org/1999/xhtml">Vanderbilt</span>
     <span class="given-names" xmlns="http://www.w3.org/1999/xhtml">D.</span>
    </name>
   </person-group>
   <div class="article-title" xmlns="http://www.w3.org/1999/xhtml">Soft self-consistent pseudopotentials in a generalized eigenvalue formalism</div>
   <div class="source" xmlns="http://www.w3.org/1999/xhtml">Phys. Rev. B</div>
   <span class="year" xmlns="http://www.w3.org/1999/xhtml">1990</span>
   <span class="volume" xmlns="http://www.w3.org/1999/xhtml">4</span>
   <span class="fpage" xmlns="http://www.w3.org/1999/xhtml">7892</span>
   <span class="lpage" xmlns="http://www.w3.org/1999/xhtml">7895</span>
   <span pub-id-type="doi" class="pub-id" xmlns="http://www.w3.org/1999/xhtml">10.1103/PhysRevB.41.7892</span>
   <?supplied-pmid 9993096?>
   <span pub-id-type="pmid" class="pub-id" xmlns="http://www.w3.org/1999/xhtml">9993096</span>
  </element-citation>
 </ref>
 <ref id="B20-molecules-24-02285" class="ref">
  <span class="label" xmlns="http://www.w3.org/1999/xhtml">20.</span>
  <element-citation publication-type="journal" class="element-citation">
   <person-group person-group-type="author" class="person-group">
    <name class="name">
     <span class="surname" xmlns="http://www.w3.org/1999/xhtml">Monkhorst</span>
     <span class="given-names" xmlns="http://www.w3.org/1999/xhtml">H.J.</span>
    </name>
    <name class="name">
     <span class="surname" xmlns="http://www.w3.org/1999/xhtml">Pack</span>
     <span class="given-names" xmlns="http://www.w3.org/1999/xhtml">J.D.</span>
    </name>
   </person-group>
   <div class="article-title" xmlns="http://www.w3.org/1999/xhtml">Special points for Brillouin-zone integrations</div>
   <div class="source" xmlns="http://www.w3.org/1999/xhtml">Phys. Rev. B Solid State</div>
   <span class="year" xmlns="http://www.w3.org/1999/xhtml">1976</span>
   <span class="volume" xmlns="http://www.w3.org/1999/xhtml">13</span>
   <span class="fpage" xmlns="http://www.w3.org/1999/xhtml">5188</span>
   <span class="lpage" xmlns="http://www.w3.org/1999/xhtml">5192</span>
   <span pub-id-type="doi" class="pub-id" xmlns="http://www.w3.org/1999/xhtml">10.1103/PhysRevB.13.5188</span>
  </element-citation>
 </ref>
 <ref id="B21-molecules-24-02285" class="ref">
  <span class="label" xmlns="http://www.w3.org/1999/xhtml">21.</span>
  <element-citation publication-type="journal" class="element-citation">
   <person-group person-group-type="author" class="person-group">
    <name class="name">
     <span class="surname" xmlns="http://www.w3.org/1999/xhtml">Pack</span>
     <span class="given-names" xmlns="http://www.w3.org/1999/xhtml">J.D.</span>
    </name>
    <name class="name">
     <span class="surname" xmlns="http://www.w3.org/1999/xhtml">Monkhorst</span>
     <span class="given-names" xmlns="http://www.w3.org/1999/xhtml">H.J.</span>
    </name>
   </person-group>
   <div class="article-title" xmlns="http://www.w3.org/1999/xhtml">Special points for Brillouin-zone integrations</div>
   <div class="source" xmlns="http://www.w3.org/1999/xhtml">Phys. Rev. B Solid State</div>
   <span class="year" xmlns="http://www.w3.org/1999/xhtml">1977</span>
   <span class="volume" xmlns="http://www.w3.org/1999/xhtml">16</span>
   <span class="fpage" xmlns="http://www.w3.org/1999/xhtml">1748</span>
   <span class="lpage" xmlns="http://www.w3.org/1999/xhtml">1749</span>
   <span pub-id-type="doi" class="pub-id" xmlns="http://www.w3.org/1999/xhtml">10.1103/PhysRevB.16.1748</span>
  </element-citation>
 </ref>
 <ref id="B22-molecules-24-02285" class="ref">
  <span class="label" xmlns="http://www.w3.org/1999/xhtml">22.</span>
  <element-citation publication-type="journal" class="element-citation">
   <person-group person-group-type="author" class="person-group">
    <name class="name">
     <span class="surname" xmlns="http://www.w3.org/1999/xhtml">Xi</span>
     <span class="given-names" xmlns="http://www.w3.org/1999/xhtml">P.</span>
    </name>
    <name class="name">
     <span class="surname" xmlns="http://www.w3.org/1999/xhtml">Shi</span>
     <span class="given-names" xmlns="http://www.w3.org/1999/xhtml">C.</span>
    </name>
    <name class="name">
     <span class="surname" xmlns="http://www.w3.org/1999/xhtml">Yan</span>
     <span class="given-names" xmlns="http://www.w3.org/1999/xhtml">P.</span>
    </name>
   </person-group>
   <div class="article-title" xmlns="http://www.w3.org/1999/xhtml">DFT study on influence of sulfur on the hydrophobicity of pyrite surfaces in the process of oxidation</div>
   <div class="source" xmlns="http://www.w3.org/1999/xhtml">App. Sur. Sci.</div>
   <span class="year" xmlns="http://www.w3.org/1999/xhtml">2019</span>
   <span class="volume" xmlns="http://www.w3.org/1999/xhtml">466</span>
   <span class="fpage" xmlns="http://www.w3.org/1999/xhtml">964</span>
   <span class="lpage" xmlns="http://www.w3.org/1999/xhtml">969</span>
   <span pub-id-type="doi" class="pub-id" xmlns="http://www.w3.org/1999/xhtml">10.1016/j.apsusc.2018.09.197</span>
  </element-citation>
 </ref>
 <ref id="B23-molecules-24-02285" class="ref">
  <span class="label" xmlns="http://www.w3.org/1999/xhtml">23.</span>
  <element-citation publication-type="journal" class="element-citation">
   <person-group person-group-type="author" class="person-group">
    <name class="name">
     <span class="surname" xmlns="http://www.w3.org/1999/xhtml">Pfrommer</span>
     <span class="given-names" xmlns="http://www.w3.org/1999/xhtml">B.</span>
    </name>
    <name class="name">
     <span class="surname" xmlns="http://www.w3.org/1999/xhtml">CÔté</span>
     <span class="given-names" xmlns="http://www.w3.org/1999/xhtml">M.</span>
    </name>
    <name class="name">
     <span class="surname" xmlns="http://www.w3.org/1999/xhtml">Louie</span>
     <span class="given-names" xmlns="http://www.w3.org/1999/xhtml">S.</span>
    </name>
    <name class="name">
     <span class="surname" xmlns="http://www.w3.org/1999/xhtml">Cohen</span>
     <span class="given-names" xmlns="http://www.w3.org/1999/xhtml">M.</span>
    </name>
   </person-group>
   <div class="article-title" xmlns="http://www.w3.org/1999/xhtml">Relaxation of crystals with the quasi-Newton method</div>
   <div class="source" xmlns="http://www.w3.org/1999/xhtml">J. Comput. Phys.</div>
   <span class="year" xmlns="http://www.w3.org/1999/xhtml">1997</span>
   <span class="volume" xmlns="http://www.w3.org/1999/xhtml">131</span>
   <span class="fpage" xmlns="http://www.w3.org/1999/xhtml">233</span>
   <span class="lpage" xmlns="http://www.w3.org/1999/xhtml">240</span>
   <span pub-id-type="doi" class="pub-id" xmlns="http://www.w3.org/1999/xhtml">10.1006/jcph.1996.5612</span>
  </element-citation>
 </ref>
 <ref id="B24-molecules-24-02285" class="ref">
  <span class="label" xmlns="http://www.w3.org/1999/xhtml">24.</span>
  <element-citation publication-type="journal" class="element-citation">
   <person-group person-group-type="author" class="person-group">
    <name class="name">
     <span class="surname" xmlns="http://www.w3.org/1999/xhtml">Xi</span>
     <span class="given-names" xmlns="http://www.w3.org/1999/xhtml">P.</span>
    </name>
    <name class="name">
     <span class="surname" xmlns="http://www.w3.org/1999/xhtml">Liu</span>
     <span class="given-names" xmlns="http://www.w3.org/1999/xhtml">W.</span>
    </name>
    <name class="name">
     <span class="surname" xmlns="http://www.w3.org/1999/xhtml">Yang</span>
     <span class="given-names" xmlns="http://www.w3.org/1999/xhtml">Z.</span>
    </name>
   </person-group>
   <div class="article-title" xmlns="http://www.w3.org/1999/xhtml">Quantum chemistry investigation on influence of sulfur atom adsorption in sulfur material to the coal pyrite hydrophobicity</div>
   <div class="source" xmlns="http://www.w3.org/1999/xhtml">J. China Coal Soc.</div>
   <span class="year" xmlns="http://www.w3.org/1999/xhtml">2017</span>
   <span class="volume" xmlns="http://www.w3.org/1999/xhtml">42</span>
   <span class="fpage" xmlns="http://www.w3.org/1999/xhtml">1290</span>
   <span class="lpage" xmlns="http://www.w3.org/1999/xhtml">1296</span>
  </element-citation>
 </ref>
 <ref id="B25-molecules-24-02285" class="ref">
  <span class="label" xmlns="http://www.w3.org/1999/xhtml">25.</span>
  <element-citation publication-type="journal" class="element-citation">
   <person-group person-group-type="author" class="person-group">
    <name class="name">
     <span class="surname" xmlns="http://www.w3.org/1999/xhtml">Han</span>
     <span class="given-names" xmlns="http://www.w3.org/1999/xhtml">Y.</span>
    </name>
    <name class="name">
     <span class="surname" xmlns="http://www.w3.org/1999/xhtml">Liu</span>
     <span class="given-names" xmlns="http://www.w3.org/1999/xhtml">W.</span>
    </name>
    <name class="name">
     <span class="surname" xmlns="http://www.w3.org/1999/xhtml">Zhou</span>
    </name>
   </person-group>
   <div class="article-title" xmlns="http://www.w3.org/1999/xhtml">Interactions between kaolinite Al-OH surface and sodium hexametaphosphate</div>
   <div class="source" xmlns="http://www.w3.org/1999/xhtml">App. Surf. Sci.</div>
   <span class="year" xmlns="http://www.w3.org/1999/xhtml">2016</span>
   <span class="volume" xmlns="http://www.w3.org/1999/xhtml">387</span>
   <span class="fpage" xmlns="http://www.w3.org/1999/xhtml">759</span>
   <span class="lpage" xmlns="http://www.w3.org/1999/xhtml">765</span>
   <span pub-id-type="doi" class="pub-id" xmlns="http://www.w3.org/1999/xhtml">10.1016/j.apsusc.2016.07.002</span>
  </element-citation>
 </ref>
 <ref id="B26-molecules-24-02285" class="ref">
  <span class="label" xmlns="http://www.w3.org/1999/xhtml">26.</span>
  <element-citation publication-type="journal" class="element-citation">
   <person-group person-group-type="author" class="person-group">
    <name class="name">
     <span class="surname" xmlns="http://www.w3.org/1999/xhtml">Han</span>
     <span class="given-names" xmlns="http://www.w3.org/1999/xhtml">Y.</span>
    </name>
    <name class="name">
     <span class="surname" xmlns="http://www.w3.org/1999/xhtml">Liu</span>
     <span class="given-names" xmlns="http://www.w3.org/1999/xhtml">W.</span>
    </name>
    <name class="name">
     <span class="surname" xmlns="http://www.w3.org/1999/xhtml">Chen</span>
    </name>
   </person-group>
   <div class="article-title" xmlns="http://www.w3.org/1999/xhtml">DFT simulation of the adsorption of sodium silicate species on kaolinite surfaces</div>
   <div class="source" xmlns="http://www.w3.org/1999/xhtml">App. Surf. Sci.</div>
   <span class="year" xmlns="http://www.w3.org/1999/xhtml">2016</span>
   <span class="volume" xmlns="http://www.w3.org/1999/xhtml">370</span>
   <span class="fpage" xmlns="http://www.w3.org/1999/xhtml">403</span>
   <span class="lpage" xmlns="http://www.w3.org/1999/xhtml">409</span>
   <span pub-id-type="doi" class="pub-id" xmlns="http://www.w3.org/1999/xhtml">10.1016/j.apsusc.2016.02.179</span>
  </element-citation>
 </ref>
 <ref id="B27-molecules-24-02285" class="ref">
  <span class="label" xmlns="http://www.w3.org/1999/xhtml">27.</span>
  <element-citation publication-type="journal" class="element-citation">
   <person-group person-group-type="author" class="person-group">
    <name class="name">
     <span class="surname" xmlns="http://www.w3.org/1999/xhtml">Yang</span>
     <span class="given-names" xmlns="http://www.w3.org/1999/xhtml">Z.</span>
    </name>
    <name class="name">
     <span class="surname" xmlns="http://www.w3.org/1999/xhtml">Liu</span>
     <span class="given-names" xmlns="http://www.w3.org/1999/xhtml">W.</span>
    </name>
    <name class="name">
     <span class="surname" xmlns="http://www.w3.org/1999/xhtml">Zhang</span>
     <span class="given-names" xmlns="http://www.w3.org/1999/xhtml">H.</span>
    </name>
   </person-group>
   <div class="article-title" xmlns="http://www.w3.org/1999/xhtml">DFT study of the adsorption of 3-chloro-2-hydroxypropyl trimethylammonium chloride on montmorillonite surfaces in solution</div>
   <div class="source" xmlns="http://www.w3.org/1999/xhtml">App. Surf. Sci.</div>
   <span class="year" xmlns="http://www.w3.org/1999/xhtml">2018</span>
   <span class="volume" xmlns="http://www.w3.org/1999/xhtml">436</span>
   <span class="fpage" xmlns="http://www.w3.org/1999/xhtml">58</span>
   <span class="lpage" xmlns="http://www.w3.org/1999/xhtml">65</span>
   <span pub-id-type="doi" class="pub-id" xmlns="http://www.w3.org/1999/xhtml">10.1016/j.apsusc.2017.12.011</span>
  </element-citation>
 </ref>
 <ref id="B28-molecules-24-02285" class="ref">
  <span class="label" xmlns="http://www.w3.org/1999/xhtml">28.</span>
  <element-citation publication-type="book" class="element-citation">
   <person-group person-group-type="author" class="person-group">
    <name class="name">
     <span class="surname" xmlns="http://www.w3.org/1999/xhtml">He</span>
     <span class="given-names" xmlns="http://www.w3.org/1999/xhtml">Q.</span>
    </name>
   </person-group>
   <div class="article-title" xmlns="http://www.w3.org/1999/xhtml">Study of Gold-Bearing Electronic Structure and Flotation Behavior</div>
   <div class="source" xmlns="http://www.w3.org/1999/xhtml">Master’ Thesis</div>
   <span class="publisher-name" xmlns="http://www.w3.org/1999/xhtml">Guangxi University</span>
   <span class="publisher-loc" xmlns="http://www.w3.org/1999/xhtml">Nanning, China</span>
   <span class="year" xmlns="http://www.w3.org/1999/xhtml">2015</span>
  </element-citation>
 </ref>
 <ref id="B29-molecules-24-02285" class="ref">
  <span class="label" xmlns="http://www.w3.org/1999/xhtml">29.</span>
  <element-citation publication-type="journal" class="element-citation">
   <person-group person-group-type="author" class="person-group">
    <name class="name">
     <span class="surname" xmlns="http://www.w3.org/1999/xhtml">Mulliken</span>
     <span class="given-names" xmlns="http://www.w3.org/1999/xhtml">R.S.</span>
    </name>
   </person-group>
   <div class="article-title" xmlns="http://www.w3.org/1999/xhtml">Electronic population analysis on LCAO-MO molecular wave functions. IV. bonding and antibonding in LCAO and Valence-bond theories</div>
   <div class="source" xmlns="http://www.w3.org/1999/xhtml">J. Chem. Phy.</div>
   <span class="year" xmlns="http://www.w3.org/1999/xhtml">1955</span>
   <span class="volume" xmlns="http://www.w3.org/1999/xhtml">23</span>
   <span class="fpage" xmlns="http://www.w3.org/1999/xhtml">2343</span>
   <span class="lpage" xmlns="http://www.w3.org/1999/xhtml">2346</span>
   <span pub-id-type="doi" class="pub-id" xmlns="http://www.w3.org/1999/xhtml">10.1063/1.1741877</span>
  </element-citation>
 </ref>
 <ref id="B30-molecules-24-02285" class="ref">
  <span class="label" xmlns="http://www.w3.org/1999/xhtml">30.</span>
  <element-citation publication-type="journal" class="element-citation">
   <person-group person-group-type="author" class="person-group">
    <name class="name">
     <span class="surname" xmlns="http://www.w3.org/1999/xhtml">Segall</span>
     <span class="given-names" xmlns="http://www.w3.org/1999/xhtml">M.D.</span>
    </name>
    <name class="name">
     <span class="surname" xmlns="http://www.w3.org/1999/xhtml">Shah</span>
     <span class="given-names" xmlns="http://www.w3.org/1999/xhtml">R.</span>
    </name>
    <name class="name">
     <span class="surname" xmlns="http://www.w3.org/1999/xhtml">Pickard</span>
     <span class="given-names" xmlns="http://www.w3.org/1999/xhtml">C.J.</span>
    </name>
    <name class="name">
     <span class="surname" xmlns="http://www.w3.org/1999/xhtml">Payne</span>
     <span class="given-names" xmlns="http://www.w3.org/1999/xhtml">M.C.</span>
    </name>
   </person-group>
   <div class="article-title" xmlns="http://www.w3.org/1999/xhtml">Population analysis of plane-wave electronic structure calculation of bulk materials</div>
   <div class="source" xmlns="http://www.w3.org/1999/xhtml">Phys. Rev. B</div>
   <span class="year" xmlns="http://www.w3.org/1999/xhtml">1996</span>
   <span class="volume" xmlns="http://www.w3.org/1999/xhtml">54</span>
   <span class="fpage" xmlns="http://www.w3.org/1999/xhtml">16317</span>
   <span class="lpage" xmlns="http://www.w3.org/1999/xhtml">16320</span>
   <span pub-id-type="doi" class="pub-id" xmlns="http://www.w3.org/1999/xhtml">10.1103/PhysRevB.54.16317</span>
   <?supplied-pmid 9985733?>
   <span pub-id-type="pmid" class="pub-id" xmlns="http://www.w3.org/1999/xhtml">9985733</span>
  </element-citation>
 </ref>
</ref-list>
