<?xml version="1.0" encoding="UTF-8"?>
<ref id="br0610" class="ref">
 <span class="label" xmlns="http://www.w3.org/1999/xhtml">61</span>
 <element-citation publication-type="journal" id="bib147DF994B983555D21EDD5449D263FCFs1" class="element-citation">
  <person-group person-group-type="author" class="person-group">
   <name class="name">
    <span class="surname" xmlns="http://www.w3.org/1999/xhtml">Guzelian</span>
    <span class="given-names" xmlns="http://www.w3.org/1999/xhtml">A.A.</span>
   </name>
   <name class="name">
    <span class="surname" xmlns="http://www.w3.org/1999/xhtml">Banin</span>
    <span class="given-names" xmlns="http://www.w3.org/1999/xhtml">U.</span>
   </name>
   <name class="name">
    <span class="surname" xmlns="http://www.w3.org/1999/xhtml">Kadavinich</span>
    <span class="given-names" xmlns="http://www.w3.org/1999/xhtml">A.V.</span>
   </name>
   <name class="name">
    <span class="surname" xmlns="http://www.w3.org/1999/xhtml">Peng</span>
    <span class="given-names" xmlns="http://www.w3.org/1999/xhtml">X.</span>
   </name>
   <name class="name">
    <span class="surname" xmlns="http://www.w3.org/1999/xhtml">Alivisatos</span>
    <span class="given-names" xmlns="http://www.w3.org/1999/xhtml">A.P.</span>
   </name>
  </person-group>
  <div class="article-title" xmlns="http://www.w3.org/1999/xhtml">Colloidal chemical synthesis and characterization of 
   <div class="inline-formula">
    <div id="M69" altimg="si64.svg" class="math">
     <span class="mi">I</span>
     <span class="mi">n</span>
     <span class="mi">A</span>
     <span class="mi">s</span>
    </div>
   </div> nanocrystal quantum dots
  </div>
  <div class="source" xmlns="http://www.w3.org/1999/xhtml">Appl. Phys. Lett.</div>
  <span class="volume" xmlns="http://www.w3.org/1999/xhtml">69</span>
  <span class="year" xmlns="http://www.w3.org/1999/xhtml">1996</span>
  <span class="fpage" xmlns="http://www.w3.org/1999/xhtml">1432</span>
  <div class="comment" xmlns="http://www.w3.org/1999/xhtml">(4 pages)</div>
 </element-citation>
 <div id="srct0310" class="mixed-citation" xmlns="http://www.w3.org/1999/xhtml">A. A. Guzelian, U. Banin, A. V. Kadavinich, X. Peng, A. P. Alivisatos, Colloidal chemical synthesis and characterization of InAs nanocrystal quantum dots, Appl. Phys. Lett. 69 (1996) 1432 (4 pages).</div>
</ref>
